afloat/__init__.py
afloat/bottom_lander.py
afloat/clean.py
afloat/currents.py
afloat/netcdf.py
afloat/operational.py
afloat/pca.py
afloat/sentinel.py
afloat/shape.py
afloat/time.py
afloat/timeseries.py
afloat/xr.py
afloat/xrwrap.py
afloat/plot/__init__.py
afloat/plot/gif.py
afloat/plot/plotting.py
afloat/sfodautils/__init__.py
afloat/sfodautils/harmonic_analysis.py
afloat/tides/__init__.py
afloat/tides/cons.py
afloat/xutils/__init__.py
afloat/xutils/windrose.py
afloat-0.0.12.dist-info/LICENSE
afloat-0.0.12.dist-info/METADATA
afloat-0.0.12.dist-info/WHEEL
afloat-0.0.12.dist-info/top_level.txt
afloat-0.0.12.dist-info/RECORD
